newauth/__init__.py
newauth/admin.py
newauth/api.py
newauth/backend.py
newauth/constants.py
newauth/decorators.py
newauth/forms.py
newauth/middleware.py
newauth/models.py
newauth/signals.py
newauth/test.py
newauth/urls.py
newauth/views.py
newauth/templates/admin/newauth/basicuser/add_form.html
newauth/templates/admin/newauth/basicuser/change_password.html
django_newauth-0.41.dist-info/LICENSE
django_newauth-0.41.dist-info/METADATA
django_newauth-0.41.dist-info/WHEEL
django_newauth-0.41.dist-info/top_level.txt
django_newauth-0.41.dist-info/RECORD
